dataq_instruments/__init__.py
dataq_instruments/_version.py
dataq_instruments/tests/__init__.py
dataq_instruments/tests/conftest.py
dataq_instruments/tests/test_examples.py
dataq_instruments-0.0.2.dist-info/AUTHORS.rst
dataq_instruments-0.0.2.dist-info/LICENSE
dataq_instruments-0.0.2.dist-info/METADATA
dataq_instruments-0.0.2.dist-info/WHEEL
dataq_instruments-0.0.2.dist-info/entry_points.txt
dataq_instruments-0.0.2.dist-info/top_level.txt
dataq_instruments-0.0.2.dist-info/RECORD
